app/__init__.py
app/errors.py
app/fusion.py
app/logger_config.py
app/metadata_types.py
app/models.py
app/py.typed
app/query_builder.py
app/server.py
app/settings.py
app/types.py
app/auth/__init__.py
app/auth/simple_token.py
app/backends/__init__.py
app/backends/base.py
app/backends/factory.py
app/backends/postgresql_backend.py
app/backends/sqlite_backend.py
app/embeddings/__init__.py
app/embeddings/base.py
app/embeddings/context_limits.py
app/embeddings/factory.py
app/embeddings/retry.py
app/embeddings/tracing.py
app/embeddings/providers/__init__.py
app/embeddings/providers/langchain_azure.py
app/embeddings/providers/langchain_huggingface.py
app/embeddings/providers/langchain_ollama.py
app/embeddings/providers/langchain_openai.py
app/embeddings/providers/langchain_voyage.py
app/migrations/__init__.py
app/migrations/add_chunking_postgresql.sql
app/migrations/add_chunking_sqlite.sql
app/migrations/add_fts_postgresql.sql
app/migrations/add_fts_sqlite.sql
app/migrations/add_jsonb_merge_patch_postgresql.sql
app/migrations/add_semantic_search_postgresql.sql
app/migrations/add_semantic_search_sqlite.sql
app/migrations/chunking.py
app/migrations/dependencies.py
app/migrations/fix_function_search_path_postgresql.sql
app/migrations/fts.py
app/migrations/metadata.py
app/migrations/semantic.py
app/migrations/utils.py
app/repositories/__init__.py
app/repositories/base.py
app/repositories/context_repository.py
app/repositories/embedding_repository.py
app/repositories/fts_repository.py
app/repositories/image_repository.py
app/repositories/statistics_repository.py
app/repositories/tag_repository.py
app/reranking/__init__.py
app/reranking/base.py
app/reranking/factory.py
app/reranking/providers/__init__.py
app/reranking/providers/flashrank.py
app/schemas/__init__.py
app/schemas/postgresql_schema.sql
app/schemas/sqlite_schema.sql
app/services/__init__.py
app/services/chunking_service.py
app/services/passage_extraction_service.py
app/startup/__init__.py
app/startup/validation.py
mcp_context_server-1.3.1.dist-info/METADATA
mcp_context_server-1.3.1.dist-info/WHEEL
mcp_context_server-1.3.1.dist-info/entry_points.txt
mcp_context_server-1.3.1.dist-info/licenses/LICENSE
mcp_context_server-1.3.1.dist-info/RECORD
