Metadata-Version: 2.4
Name: mcp-context-server
Version: 1.3.1
Summary: MCP Context Server — a FastMCP-based server providing persistent multimodal context storage for LLM agents.
Author-email: Aleksandr Filippov <alexfeel@protonmail.com>
License-File: LICENSE
Requires-Python: <3.13,>=3.12
Requires-Dist: anyio==4.12.1
Requires-Dist: asyncpg==0.31.0
Requires-Dist: fastmcp==2.14.4
Requires-Dist: pydantic-settings==2.12.0
Requires-Dist: pydantic==2.12.5
Requires-Dist: python-dotenv==1.2.1
Requires-Dist: tenacity==9.1.2
Requires-Dist: typing-extensions==4.15.0
Provides-Extra: embeddings-all
Requires-Dist: langchain-huggingface>=0.2.0; extra == 'embeddings-all'
Requires-Dist: langchain-ollama>=0.3.0; extra == 'embeddings-all'
Requires-Dist: langchain-openai>=0.3.0; extra == 'embeddings-all'
Requires-Dist: langchain-text-splitters>=0.3.0; extra == 'embeddings-all'
Requires-Dist: langchain-voyageai>=0.3.0; extra == 'embeddings-all'
Requires-Dist: numpy>=2.4.1; extra == 'embeddings-all'
Requires-Dist: pgvector>=0.4.0; extra == 'embeddings-all'
Requires-Dist: sqlite-vec>=0.1.6; extra == 'embeddings-all'
Provides-Extra: embeddings-azure
Requires-Dist: langchain-openai>=0.3.0; extra == 'embeddings-azure'
Requires-Dist: langchain-text-splitters>=0.3.0; extra == 'embeddings-azure'
Requires-Dist: numpy>=2.4.1; extra == 'embeddings-azure'
Requires-Dist: pgvector>=0.4.0; extra == 'embeddings-azure'
Requires-Dist: sqlite-vec>=0.1.6; extra == 'embeddings-azure'
Provides-Extra: embeddings-huggingface
Requires-Dist: langchain-huggingface>=0.2.0; extra == 'embeddings-huggingface'
Requires-Dist: langchain-text-splitters>=0.3.0; extra == 'embeddings-huggingface'
Requires-Dist: numpy>=2.4.1; extra == 'embeddings-huggingface'
Requires-Dist: pgvector>=0.4.0; extra == 'embeddings-huggingface'
Requires-Dist: sqlite-vec>=0.1.6; extra == 'embeddings-huggingface'
Provides-Extra: embeddings-ollama
Requires-Dist: langchain-ollama>=0.3.0; extra == 'embeddings-ollama'
Requires-Dist: langchain-text-splitters>=0.3.0; extra == 'embeddings-ollama'
Requires-Dist: numpy>=2.4.1; extra == 'embeddings-ollama'
Requires-Dist: pgvector>=0.4.0; extra == 'embeddings-ollama'
Requires-Dist: sqlite-vec>=0.1.6; extra == 'embeddings-ollama'
Provides-Extra: embeddings-openai
Requires-Dist: langchain-openai>=0.3.0; extra == 'embeddings-openai'
Requires-Dist: langchain-text-splitters>=0.3.0; extra == 'embeddings-openai'
Requires-Dist: numpy>=2.4.1; extra == 'embeddings-openai'
Requires-Dist: pgvector>=0.4.0; extra == 'embeddings-openai'
Requires-Dist: sqlite-vec>=0.1.6; extra == 'embeddings-openai'
Provides-Extra: embeddings-voyage
Requires-Dist: langchain-text-splitters>=0.3.0; extra == 'embeddings-voyage'
Requires-Dist: langchain-voyageai>=0.3.0; extra == 'embeddings-voyage'
Requires-Dist: numpy>=2.4.1; extra == 'embeddings-voyage'
Requires-Dist: pgvector>=0.4.0; extra == 'embeddings-voyage'
Requires-Dist: sqlite-vec>=0.1.6; extra == 'embeddings-voyage'
Provides-Extra: langsmith
Requires-Dist: langsmith>=0.4.0; extra == 'langsmith'
Provides-Extra: reranking
Requires-Dist: flashrank>=0.2.0; extra == 'reranking'
Provides-Extra: search-quality
Requires-Dist: flashrank>=0.2.0; extra == 'search-quality'
Requires-Dist: langchain-text-splitters>=0.3.0; extra == 'search-quality'
